{
  "Suite2": {
    "Name": "Validation of student assignment detail list",
    "TestCaseRepo": [
      "./testResources/testcaseRepository/engageExperienceApp/EngageTCRepository.json"
    ],
    "Before": [
      {
        "id": "launchUrl",
        "description": "",
        "testFile": "./engageAutomation/core/runner/launchUrl.js",
        "testData": []
      },
      {
        "id": "ENG_LAND_TC_3",
        "description": "",
        "testFile": "./test/engageExperienceApp/landing.test.js",
        "testData": []
      },
      {
        "id": "ENG_IDEN_TC_7",
        "description": "",
        "testFile": "./test/engageExperienceApp/login.test.js",
        "testData": [
          {
            "dataFile": "./testResources/testcaseData/difusionExperienceApp/qa/logindata.json",
            "jsonPath": "engage.login.user.assignmentStudent"
          }
        ]
      }
   
    ],
    "BeforeEach": [],
    "Test": [
      {
        "id": "ENG_ASSLIST_STU_TC_4",
        "description": "",
        "testFile": "./test/engageExperienceApp/assignmentListDetails_students.test.js",
        "testData": [
          {
            "dataFile": "./testResources/testcaseData/difusionExperienceApp/qa/appLangEN.json",
            "jsonPath": "engage.appContent.assignmentList.student"
          }
        ]
      },
      {
        "id": "ENG_ASSLIST_STU_TC_8",
        "description": "",
        "testFile": "./test/engageExperienceApp/assignmentListDetails_students.test.js",
        "testData": [
          {
            "dataFile": "./testResources/testcaseData/difusionExperienceApp/qa/assignmentData.json",
            "jsonPath": "engage.assignmentList.student.dueAssignmentNames"
          }
        ]
      },
      {
        "id": "ENG_ASSLIST_STU_TC_5",
        "description": "",
        "testFile": "./test/engageExperienceApp/assignmentListDetails_students.test.js",
        "testData": [
          {
            "dataFile": "./testResources/testcaseData/difusionExperienceApp/qa/appLangEN.json",
            "jsonPath": "engage.appContent.assignmentList.student"
          }
        ]
      },
      {
        "id": "ENG_ASSLIST_STU_TC_8",
        "description": "",
        "testFile": "./test/engageExperienceApp/assignmentListDetails_students.test.js",
        "testData": [
          {
            "dataFile": "./testResources/testcaseData/difusionExperienceApp/qa/assignmentData.json",
            "jsonPath": "engage.assignmentList.student.upcomingAssignmentNames"
          }
        ]
      },
      {
        "id": "ENG_ASSLIST_STU_TC_6",
        "description": "",
        "testFile": "./test/engageExperienceApp/assignmentListDetails_students.test.js",
        "testData": [
          {
            "dataFile": "./testResources/testcaseData/difusionExperienceApp/qa/appLangEN.json",
            "jsonPath": "engage.appContent.assignmentList.student"
          }
        ]
      },
      {
        "id": "ENG_ASSLIST_STU_TC_8",
        "description": "",
        "testFile": "./test/engageExperienceApp/assignmentListDetails_students.test.js",
        "testData": [
          {
            "dataFile": "./testResources/testcaseData/difusionExperienceApp/qa/assignmentData.json",
            "jsonPath": "engage.assignmentList.student.completedAssignmentNames"
          }
        ]
      },
      {
        "id": "ENG_ASSLIST_STU_TC_9",
        "description": "Validate clicking on Show Activities button",
        "testFile": "./test/engageExperienceApp/assignmentListDetails_students.test.js",
        "testData": [
          {
            "dataFile": "./testResources/testcaseData/difusionExperienceApp/qa/assignmentData.json",
            "jsonPath": "engage.assignmentList.student.completedAssignmentNames"
          },
          {
            "dataFile": "./testResources/testcaseData/difusionExperienceApp/qa/assignmentData.json",
            "jsonPath": "engage.assignmentList.student.completedAssignmentActivityList"
          },
          {
            "dataFile": "./testResources/testcaseData/difusionExperienceApp/qa/appLangEN.json",
            "jsonPath": "engage.appContent.assignmentList.student"
          }
        ]
      }
    ],
    "AfterEach": [],
    "After": []
  }
}